{
  "title": {
    "en": "Mode has changed",
    "nl": "Modus gewijzigd",
    "de": "Modus hat sich geändert",
    "da": "Tilstand er ændret",
    "es": "El modo ha cambiado",
    "fr": "Le mode a changé",
    "it": "La modalità è cambiata",
    "no": "Modus er endret",
    "sv": "Läget har ändrats",
    "pl": "Tryb został zmieniony",
    "ru": "Режим изменился",
    "ko": "모드가 변경되었습니다"
  },
  "tokens": [
    {
      "name": "new_mode",
      "type": "string",
      "title": {
        "en": "new mode",
        "nl": "nieuwe modus",
        "de": "neue modus",
        "da": "ny tilstand",
        "es": "nuevo modo",
        "fr": "nouveau mode",
        "it": "nuova modalità",
        "no": "ny modus",
        "sv": "nytt läge",
        "pl": "nowy tryb",
        "ru": "новый режим",
        "ko": "새로운 모드"
      },
      "example": "medium"
    },
    {
      "name": "previous_mode",
      "type": "string",
      "title": {
        "en": "previous mode",
        "nl": "vorige modus",
        "de": "bisherige modus",
        "da": "forrige tilstand",
        "es": "modo anterior",
        "fr": "mode précédent",
        "it": "modalità precedente",
        "no": "forrige modus",
        "sv": "föregående läge",
        "pl": "poprzedni tryb",
        "ru": "предыдущий режим",
        "ko": "이전 모드"
      },
      "example": "silent"
    }
  ],
  "args": [
    {
      "name": "device",
      "type": "device",
      "placeholder": {
        "en": "Select Device",
        "nl": "Selecteer apparaat",
        "da": "Vælg enhed",
        "es": "Seleccione dispositivo",
        "fr": "Sélectionnez l'appareil",
        "it": "Seleziona dispositivo",
        "no": "Velg enhet",
        "sv": "Välj enhet",
        "pl": "Wybierz urządzenie",
        "ru": "Выберите устройство",
        "ko": "디바이스 선택"
      },
      "filter": "driver_id=mi-airpurifier|airpurifier_zhimi_advanced|airpurifier_zhimi_advanced_miot|airpurifier_zhimi_airpurifier_ma2|airpurifier_dmaker_airfresh_t2017|airfresh_zhimi_airfresh|humidifier_zhimi_humidifier|humidifier_zhimi_humidifier_miot|humidifier_deerma_humidifier_jsq|humidifier_deerma_humidifier_miot|dmaker_fan_1c|fan_zhimi_advanced|zhimi_fan_za5|airfryer_careli_miot|petwaterdispenser_mmgg_miot|petfeeder_mmgg_miot|humidifier_xiaomi_humidifier|dehumidifier_dmaker_derh_miot"
    }
  ],
  "platforms": [
    "local"
  ]
}